django_jwt_decorator/__init__.py
django_jwt_decorator/django_jwt_decorator.py
django_jwt_decorator-0.0.2.dist-info/LICENSE
django_jwt_decorator-0.0.2.dist-info/METADATA
django_jwt_decorator-0.0.2.dist-info/WHEEL
django_jwt_decorator-0.0.2.dist-info/top_level.txt
django_jwt_decorator-0.0.2.dist-info/RECORD
