Metadata-Version: 2.1
Name: django-jwt-decorator
Version: 0.0.2
Summary: View authentication decorator based on django json web token
Home-page: https://github.com/505598397/django-jwt-decorator
Author: sunwei
Author-email: 505598397@qq.com
License: UNKNOWN
Platform: UNKNOWN
Classifier: Programming Language :: Python :: 3
Classifier: License :: OSI Approved :: MIT License
Classifier: Operating System :: OS Independent
Requires-Dist: pyjwt
